multiprogress/__init__.py
multiprogress/aio.py
multiprogress/marimo/__init__.py
multiprogress/marimo/aio.py
multiprogress/multi_tasks.py
multiprogress/parallel.py
multiprogress/py.typed
multiprogress/table.py
multiprogress-0.4.1.dist-info/WHEEL
multiprogress-0.4.1.dist-info/METADATA
multiprogress-0.4.1.dist-info/RECORD
