Metadata-Version: 2.3
Name: multiprogress
Version: 0.4.1
Summary: A Python package for displaying progress of multiple tasks.
Author: daizutabi
Author-email: daizutabi <daizutabi@gmail.com>
License: MIT License
Classifier: Programming Language :: Python
Classifier: Programming Language :: Python :: 3.10
Classifier: Programming Language :: Python :: 3.11
Classifier: Programming Language :: Python :: 3.12
Classifier: Programming Language :: Python :: 3.13
Classifier: Programming Language :: Python :: 3.14
Requires-Dist: joblib
Requires-Dist: rich
Requires-Dist: watchfiles
Requires-Python: >=3.10
Project-URL: Documentation, https://github.com/daizutabi/multiprogress
Project-URL: Issues, https://github.com/daizutabi/multiprogress/issues
Project-URL: Source, https://github.com/daizutabi/multiprogress
